image_processing_ajs/__init__.py
image_processing_ajs/processing/__init__.py
image_processing_ajs/processing/color.py
image_processing_ajs/processing/exposure.py
image_processing_ajs/processing/io.py
image_processing_ajs/processing/measure.py
image_processing_ajs/processing/plot.py
image_processing_ajs/tests/__init__.py
image_processing_ajs/tests/test_color.py
image_processing_ajs/tests/test_exposure.py
image_processing_ajs/tests/test_io.py
image_processing_ajs/tests/test_measure.py
image_processing_ajs/tests/test_plot.py
image_processing_ajs-0.1.2.dist-info/METADATA
image_processing_ajs-0.1.2.dist-info/WHEEL
image_processing_ajs-0.1.2.dist-info/top_level.txt
image_processing_ajs-0.1.2.dist-info/RECORD
