Metadata-Version: 2.1
Name: image-processing-ajs
Version: 0.1.2
Summary: A package for image processing using Python
Home-page: https://github.com/soaresaj/image-processing-ajs-package
Author: Antonio José Soares
Author-email: soaresaj@terra.com.br
Classifier: Programming Language :: Python :: 3
Classifier: License :: OSI Approved :: MIT License
Classifier: Operating System :: OS Independent
Requires-Python: >=3.6
Requires-Dist: numpy>=1.21.0
Requires-Dist: scikit-image>=0.18.0
Requires-Dist: matplotlib>=3.3.0
